elfa/__init__.py
elfa/attr_maps.py
elfa/constants.py
elfa/conv_process.py
elfa/criteria.py
elfa/inversion.py
elfa/layerfa.py
elfa/loadshow.py
elfa/plot_module.py
elfa/utils.py
elfa-0.0.5.dist-info/METADATA
elfa-0.0.5.dist-info/WHEEL
elfa-0.0.5.dist-info/licenses/LICENSE
elfa-0.0.5.dist-info/RECORD
