Metadata-Version: 2.4
Name: elfa
Version: 0.0.5
Summary: Explanatory Factor Analysis for CNNs
Author: Clara I. López-González
License-Expression: MIT
License-File: LICENSE
Requires-Python: >=3.13
Requires-Dist: factor-analyzer>=0.5.1
Requires-Dist: ipython>=9.4.0
Requires-Dist: matplotlib>=3.10.5
Requires-Dist: numpy>=2.3.2
Requires-Dist: scikit-learn>=1.7.1
Requires-Dist: tensorflow-datasets>=4.9.9
Requires-Dist: tensorflow[and-cuda]>=2.20.0
